kirsche/__init__.py
kirsche/command.py
kirsche/connect.py
kirsche/dataset.py
kirsche/download.py
kirsche/utils/__init__ copy.py
kirsche/utils/__init__.py
kirsche/utils/bib.py
kirsche/utils/constants.py
kirsche/utils/graph.py
kirsche/utils/io.py
kirsche/utils/semanticscholar.py
kirsche/utils/web.py
kirsche/version.py
kirsche/visualize.py
kirsche-0.2.9.dist-info/LICENSE
kirsche-0.2.9.dist-info/METADATA
kirsche-0.2.9.dist-info/WHEEL
kirsche-0.2.9.dist-info/entry_points.txt
kirsche-0.2.9.dist-info/RECORD
