Metadata-Version: 2.1
Name: kirsche
Version: 0.2.9
Summary: Kirsche is a python package to build up connections between papers.
License: MIT
Author: LM
Author-email: hi@leima.is
Requires-Python: >=3.9,<4.0
Classifier: License :: OSI Approved :: MIT License
Classifier: Programming Language :: Python :: 3
Classifier: Programming Language :: Python :: 3.9
Classifier: Programming Language :: Python :: 3.10
Classifier: Programming Language :: Python :: 3.11
Classifier: Programming Language :: Python :: 3.12
Requires-Dist: bibtexparser (>=1.2.0,<2.0.0)
Requires-Dist: click (>=8.1.7,<9.0.0)
Requires-Dist: loguru (>=0.5.3,<0.6.0)
Requires-Dist: matplotlib (>=3.4.3,<4.0.0)
Requires-Dist: nose (>=1.3.7,<2.0.0)
Requires-Dist: openpyxl (>=3.0.7,<4.0.0)
Requires-Dist: pandas (>=1.0.0,<2.0.0)
Requires-Dist: pyecharts (>=1.5.0,<2.0.0)
Requires-Dist: requests (>=2.26.0,<3.0.0)
